README.rst
setup.py
ecopad/__init__.py
ecopad/launch.py
ecopad/main.py
ecopad.egg-info/PKG-INFO
ecopad.egg-info/SOURCES.txt
ecopad.egg-info/dependency_links.txt
ecopad.egg-info/entry_points.txt
ecopad.egg-info/not-zip-safe
ecopad.egg-info/requires.txt
ecopad.egg-info/top_level.txt