Metadata-Version: 1.1
Name: ecopad
Version: 1.0
Summary: Text padding for Eco the game
Home-page: https://github.com/morngrar/ecopad
Author: Svein-Kåre Bjørnsen
Author-email: sveinkare@gmail.com
License: GPL
Platform: UNKNOWN
Classifier: Development Status :: 4 - Beta
Classifier: Intended Audience :: End Users/Desktop
Classifier: License :: OSI Approved :: GNU General Public License v3 (GPLv3)
Classifier: Programming Language :: Python :: 3
Classifier: Topic :: Utilities
